benchlab/__init__.py
benchlab/version.py
benchlab/core/__init__.py
benchlab/core/sensor_translation.py
benchlab/core/serial_io.py
benchlab/core/structures.py
benchlab/core/utils.py
benchlab_pycore-0.1.1.dist-info/licenses/LICENSE
tests/__init__.py
tests/test_core.py
benchlab_pycore-0.1.1.dist-info/METADATA
benchlab_pycore-0.1.1.dist-info/WHEEL
benchlab_pycore-0.1.1.dist-info/top_level.txt
benchlab_pycore-0.1.1.dist-info/RECORD
