Metadata-Version: 2.4
Name: benchlab-pycore
Version: 0.1.1
Summary: BENCHLAB PyCore - Python Interface for BENCHLAB
Home-page: https://github.com/BenchLab-io/benchlab-pycore
Author: Pieter Plaisier
Author-email: Pieter Plaisier <contact@benchlab.io>
License: MIT
Project-URL: Homepage, https://github.com/BenchLab-io/benchlab-pycore
Project-URL: Issues, https://github.com/BenchLab-io/benchlab-pycore/issues
Keywords: telemetry,hardware,benchlab,sensors
Classifier: Programming Language :: Python :: 3
Classifier: License :: OSI Approved :: MIT License
Classifier: Operating System :: OS Independent
Requires-Python: >=3.8
License-File: LICENSE
Requires-Dist: pyserial>=3.5
Dynamic: license-file
